vbrpytools/__init__.py
vbrpytools/dicjsontools.py
vbrpytools/exceltojson.py
vbrpytools/exceptions.py
vbrpytools/misctools.py
vbrpytools-3.9.1.dist-info/METADATA
vbrpytools-3.9.1.dist-info/WHEEL
vbrpytools-3.9.1.dist-info/entry_points.txt
vbrpytools-3.9.1.dist-info/licenses/LICENSE
vbrpytools-3.9.1.dist-info/RECORD
