Metadata-Version: 2.4
Name: vbrpytools
Version: 3.9.1
Summary: Package grouping functions that I'm using in multiple places
Project-URL: Documentation, https://github.com/vbrett/vbrpytools/blob/master/README.md
Project-URL: source, https://github.com/vbrett/vbrpytools
Project-URL: Repository, https://github.com/vbrett/vbrpytools.git
Project-URL: Issues, https://github.com/vbrett/vbrpytools/issues
Author-email: Vincent Brettnacher <vincent.brettnacher@veoneer.com>
License: MIT License
License-File: LICENSE
Keywords: development,personal,tools,utilities
Classifier: Intended Audience :: Developers
Classifier: License :: OSI Approved :: MIT License
Classifier: Operating System :: Microsoft :: Windows :: Windows 10
Classifier: Operating System :: Microsoft :: Windows :: Windows 11
Classifier: Operating System :: POSIX :: Linux
Classifier: Programming Language :: Python
Classifier: Programming Language :: Python :: 3 :: Only
Classifier: Programming Language :: Python :: 3.10
Classifier: Programming Language :: Python :: 3.13
Requires-Python: >=3.10
Requires-Dist: humanize>=4.14.0
Requires-Dist: openpyxl>=3.1.5
